CHANGES.txt
COPYRIGHT.txt
LICENSE.txt
MANIFEST.in
README.txt
setup.py
src/cipher/__init__.py
src/cipher.lazydate.egg-info/PKG-INFO
src/cipher.lazydate.egg-info/SOURCES.txt
src/cipher.lazydate.egg-info/dependency_links.txt
src/cipher.lazydate.egg-info/not-zip-safe
src/cipher.lazydate.egg-info/requires.txt
src/cipher.lazydate.egg-info/top_level.txt
src/cipher/lazydate/__init__.py
src/cipher/lazydate/interfaces.py
src/cipher/lazydate/lazydate.py
src/cipher/lazydate/tests.py
src/cipher/lazydate/parsedatetime/__init__.py
src/cipher/lazydate/parsedatetime/parsedatetime.py
src/cipher/lazydate/parsedatetime/parsedatetime_consts.py
src/cipher/lazydate/parsedatetime/t2.py